edc_offstudy/__init__.py
edc_offstudy/action_items.py
edc_offstudy/admin.py
edc_offstudy/admin_site.py
edc_offstudy/apps.py
edc_offstudy/auth_objects.py
edc_offstudy/auths.py
edc_offstudy/choices.py
edc_offstudy/constants.py
edc_offstudy/exceptions.py
edc_offstudy/models.py
edc_offstudy/offline_models.py
edc_offstudy/urls.py
edc_offstudy/utils.py
edc_offstudy/migrations/0001_initial.py
edc_offstudy/migrations/0002_auto_20180921_0434.py
edc_offstudy/migrations/0003_auto_20181108_0353.py
edc_offstudy/migrations/0004_auto_20190114_0250.py
edc_offstudy/migrations/0005_auto_20190305_0123.py
edc_offstudy/migrations/0006_auto_20190922_0439.py
edc_offstudy/migrations/0007_auto_20191024_1000.py
edc_offstudy/migrations/0008_auto_20191102_0033.py
edc_offstudy/migrations/0009_auto_20200513_0023.py
edc_offstudy/migrations/0010_auto_20220704_1841.py
edc_offstudy/migrations/0011_auto_20220714_2136.py
edc_offstudy/migrations/0012_rename_offstudy_reason_other_historicalsubjectoffstudy_other_offstudy_reason_and_more.py
edc_offstudy/migrations/0013_alter_historicalsubjectoffstudy_options_and_more.py
edc_offstudy/migrations/0014_auto_20220918_0508.py
edc_offstudy/migrations/0015_auto_20220925_0032.py
edc_offstudy/migrations/0016_auto_20220929_1742.py
edc_offstudy/migrations/0017_alter_subjectoffstudy_options.py
edc_offstudy/migrations/0018_alter_subjectoffstudy_managers.py
edc_offstudy/migrations/0019_alter_historicalsubjectoffstudy_device_created_and_more.py
edc_offstudy/migrations/0020_alter_subjectoffstudy_options_and_more.py
edc_offstudy/migrations/0021_remove_historicalsubjectoffstudy_consent_model_and_more.py
edc_offstudy/migrations/__init__.py
edc_offstudy/model_mixins/__init__.py
edc_offstudy/model_mixins/offstudy_crf_model_mixin.py
edc_offstudy/model_mixins/offstudy_model_mixin.py
edc_offstudy/model_mixins/offstudy_non_crf_model_mixin.py
edc_offstudy/modelform_mixins/__init__.py
edc_offstudy/modelform_mixins/offstudy_modelform_mixins.py
edc_offstudy-1.0.1.dist-info/licenses/AUTHORS
edc_offstudy-1.0.1.dist-info/licenses/LICENSE
edc_offstudy-1.0.1.dist-info/METADATA
edc_offstudy-1.0.1.dist-info/WHEEL
edc_offstudy-1.0.1.dist-info/top_level.txt
edc_offstudy-1.0.1.dist-info/RECORD
